ibkrbox/__init__.py
ibkrbox/cli.py
ibkrbox/ibkrbox.py
ibkrbox-0.6.0.dist-info/METADATA
ibkrbox-0.6.0.dist-info/entry_points.txt
ibkrbox-0.6.0.dist-info/LICENSE
ibkrbox-0.6.0.dist-info/WHEEL
ibkrbox-0.6.0.dist-info/RECORD
