Metadata-Version: 2.1
Name: ibkrbox
Version: 0.6.0
Summary: box spread utility for interactive brokers
Home-page: https://github.com/asemx/ibkrbox
Author: asemx
Author-email: 998264+asemx@users.noreply.github.com
Requires-Python: >=3.8,<4.0
Classifier: Programming Language :: Python :: 3
Classifier: Programming Language :: Python :: 3.8
Classifier: Programming Language :: Python :: 3.9
Classifier: Programming Language :: Python :: 3.10
Classifier: Programming Language :: Python :: 3.11
Requires-Dist: click (>=8.1.3,<9.0.0)
Requires-Dist: click-log (>=0.4.0,<0.5.0)
Requires-Dist: ib-insync (>=0.9.71,<0.10.0)
Requires-Dist: pandas (>=1.5.1,<2.0.0)
Project-URL: Documentation, https://github.com/asemx/ibkrbox/blob/main/README.md
Project-URL: Repository, https://github.com/asemx/ibkrbox.git
